LICENSE
MANIFEST.in
README.rst
setup.py
terminal/__init__.py
terminal/color.py
terminal/command.py
terminal/log.py
terminal/prompt.py
terminal.egg-info/PKG-INFO
terminal.egg-info/SOURCES.txt
terminal.egg-info/dependency_links.txt
terminal.egg-info/top_level.txt