Metadata-Version: 1.0
Name: terminal
Version: 0.1.0
Summary: 
